mqttstuff/__init__.py
mqttstuff/mosquittomqttwrapper.py
mqttstuff/py.typed
mqttstuff-0.0.5.dist-info/METADATA
mqttstuff-0.0.5.dist-info/WHEEL
mqttstuff-0.0.5.dist-info/licenses/LICENSE.md
mqttstuff-0.0.5.dist-info/RECORD
