Metadata-Version: 2.4
Name: mqttstuff
Version: 0.0.5
Summary: MQTTStuff
Project-URL: Homepage, https://github.com/vroomfondel/mqttstuff
Project-URL: Repository, https://github.com/vroomfondel/mqttstuff
Project-URL: Issues, https://github.com/vroomfondel/mqttstuff/issues
Author-email: Henning Thieß <ht@xomox.cc>
License-File: LICENSE.md
Keywords: home-automation,iot,library,messaging,mqtt,paho-mqtt,publish-subscribe,python
Classifier: Development Status :: 5 - Production/Stable
Classifier: License :: OSI Approved :: GNU Lesser General Public License v3 or later (LGPLv3+)
Classifier: Operating System :: OS Independent
Classifier: Programming Language :: Python :: 3
Classifier: Topic :: Home Automation
Classifier: Topic :: Internet
Classifier: Topic :: Software Development :: Libraries
Classifier: Topic :: Software Development :: Libraries :: Python Modules
Requires-Python: >=3.12
Requires-Dist: loguru>=0.7.3
Requires-Dist: paho-mqtt>=2.1.0
Requires-Dist: pydantic>=2.11.0
Requires-Dist: pytz>=2025.2
